LICENSE
README.md
setup.py
mobile_translation_manager.egg-info/PKG-INFO
mobile_translation_manager.egg-info/SOURCES.txt
mobile_translation_manager.egg-info/dependency_links.txt
mobile_translation_manager.egg-info/requires.txt
mobile_translation_manager.egg-info/top_level.txt
mtm/__init__.py
mtm/android.py
mtm/ios.py
mtm/manager.py
mtm/map.py
mtm/sheets.py
mtm/strings.py
mtm/utilities.py