Metadata-Version: 2.1
Name: mobile-translation-manager
Version: 0.0.3
Summary: A library that aims to simplify managing translations for iOS and Android applications.
Home-page: https://github.com/sethwhite2/mobile-translation-manager
Author: Seth White
Author-email: flying.squirrel.development@gmail.com
License: MIT
Keywords: translations localizations android ios manager manage simplify simple strings string language languages app apps applicaiton applications
Platform: UNKNOWN
License-File: LICENSE
